sdk_mocks/MockManager.py
sdk_mocks/__init__.py
sdk_mocks-0.1.0.dist-info/LICENSE
sdk_mocks-0.1.0.dist-info/METADATA
sdk_mocks-0.1.0.dist-info/WHEEL
sdk_mocks-0.1.0.dist-info/top_level.txt
sdk_mocks-0.1.0.dist-info/RECORD
