Metadata-Version: 2.1
Name: sdk_mocks
Version: 0.1.0
Summary: A library of pre-built mocks for popular Python SDKs.
Author: BlaiseLabs
Author-email: blaiselabs@gmail.com
Requires-Python: >=3.6
License-File: LICENSE
